wagtailformblocks/__init__.py
wagtailformblocks/apps.py
wagtailformblocks/blocks.py
wagtailformblocks/chooser.py
wagtailformblocks/forms.py
wagtailformblocks/models.py
wagtailformblocks/urls.py
wagtailformblocks/views.py
wagtailformblocks/wagtail_hooks.py
wagtailformblocks/widgets.py
wagtailformblocks/migrations/0001_initial.py
wagtailformblocks/migrations/0002_baseform_add_recaptcha.py
wagtailformblocks/migrations/0003_add_hidden_field.py
wagtailformblocks/migrations/0004_formfield_clean_name.py
wagtailformblocks/migrations/0005_alter_formfield_choices_alter_formfield_clean_name_and_more.py
wagtailformblocks/migrations/__init__.py
wagtailformblocks/static/wagtailformblocks/js/formhandler.js
wagtailformblocks/templates/wagtailformblocks/form_block.html
wagtailformblocks/utils/__init__.py
wagtailformblocks/utils/conf.py
wagtailformblocks-0.10.1.dist-info/AUTHORS.rst
wagtailformblocks-0.10.1.dist-info/LICENSE
wagtailformblocks-0.10.1.dist-info/METADATA
wagtailformblocks-0.10.1.dist-info/WHEEL
wagtailformblocks-0.10.1.dist-info/top_level.txt
wagtailformblocks-0.10.1.dist-info/RECORD
